<?xml version="1.0" encoding="UTF-8"?>
<!DOCTYPE mapper PUBLIC "-//mybatis.org//DTD Mapper 3.0//EN" "http://mybatis.org/dtd/mybatis-3-mapper.dtd">

<mapper namespace="io.renren.modules.sys.dao.FactorTableDao">

    <!-- 可根据自己的需求，是否要使用 -->
    <resultMap type="io.renren.modules.sys.entity.FactorTableEntity" id="factorTableMap">
        <result property="id" column="id"/>
        <result property="featureId" column="feature_id"/>
        <result property="materialName" column="material_name"/>
        <result property="unit" column="unit"/>
        <result property="factor1" column="factor1"/>
        <result property="factor2" column="factor2"/>
        <result property="stdError" column="std_error"/>
        <result property="createdTime" column="created_time"/>
    </resultMap>
    <select id="getFactorTableById" resultType="io.renren.modules.sys.entity.FactorTableEntity"
            parameterType="java.util.Map">
        SELECT * FROM factor_table WHERE feature_id=#{featureId}
    </select>


</mapper>